logspend_sdk/__init__.py
logspend_sdk/constants.py
logspend_sdk/core.py
logspend_sdk/integrations.py
logspend_sdk/test_logspend_integration.py
logspend_sdk-1.4.0.dist-info/METADATA
logspend_sdk-1.4.0.dist-info/WHEEL
logspend_sdk-1.4.0.dist-info/top_level.txt
logspend_sdk-1.4.0.dist-info/RECORD
