Metadata-Version: 2.1
Name: logspend-sdk
Version: 1.4.0
Summary: SDK for sending LLM application logs to LogSpend
Author: Victor Chima
Author-email: hello@logspend.com
Keywords: logging LLM LogSpend SDK
Requires-Dist: httpx ==0.25.0
Requires-Dist: langchain >=0.1.0
